willowspreadsheet/__init__.py
willowspreadsheet/willowspreadsheet.py
willowspreadsheet-0.1.2.dist-info/METADATA
willowspreadsheet-0.1.2.dist-info/WHEEL
willowspreadsheet-0.1.2.dist-info/RECORD
