Metadata-Version: 2.1
Name: willowspreadsheet
Version: 0.1.2
Summary: 
Author: willow
Author-email: brmagrini@gmail.com
Requires-Python: >=3.11,<4.0
Classifier: Programming Language :: Python :: 3
Classifier: Programming Language :: Python :: 3.11
Requires-Dist: gspread (>=5.10.0,<6.0.0)
Requires-Dist: oauth2client (>=4.1.3,<5.0.0)
